client/__init__.py
client/client.py
client/common/__init__.py
client/common/add_contact.py
client/common/database.py
client/common/del_contact.py
client/common/errors.py
client/common/main_window.py
client/common/main_window_conv.py
client/common/metaclasses.py
client/common/start_dialog.py
client/common/transport.py
client/common/utils.py
client/common/variables.py
client/logs/__init__.py
client/logs/config_client_log.py
client/logs/decorator_logs.py
client/unit_tests/__init__.py
client/unit_tests/test_utils.py
server/__init__.py
server/server.py
server/common/__init__.py
server/common/descriptors.py
server/common/errors.py
server/common/metaclasses.py
server/common/utils.py
server/common/variables.py
server/logs/__init__.py
server/logs/config_server_log.py
server/logs/decorator_logs.py
server/server/__init__.py
server/server/add_user.py
server/server/config_window.py
server/server/core.py
server/server/database.py
server/server/decorators.py
server/server/main_window.py
server/server/remove_user.py
server/server/stat_window.py
asynchronous_chat-1.0.0.dist-info/METADATA
asynchronous_chat-1.0.0.dist-info/WHEEL
asynchronous_chat-1.0.0.dist-info/top_level.txt
asynchronous_chat-1.0.0.dist-info/RECORD
