Metadata-Version: 2.1
Name: asynchronous_chat
Version: 1.0.0
Summary: mess_client
Author: @k2Fox
Author-email: k2foxspb@mail.ru
Requires-Dist: PyQt5
Requires-Dist: sqlalchemy
Requires-Dist: pycryptodome
Requires-Dist: pycryptodomex
